{"chunk_definitions":[{"row":22,"row_count":1,"visible":true,"expansion_state":0,"options":{"engine":"r","label":"setup","include":false,"dev":"png"},"document_id":"2F1DCE16","chunk_id":"csetup_chunk","chunk_label":"setup"},{"row":62,"row_count":1,"visible":true,"expansion_state":0,"options":{"engine":"r","label":"yearly_revenue","dev":"png"},"document_id":"2F1DCE16","chunk_id":"cslbazd3u1pyd","chunk_label":"yearly_revenue"},{"row":91,"row_count":1,"visible":true,"expansion_state":0,"options":{"engine":"r","label":"top_unit","dev":"png"},"document_id":"2F1DCE16","chunk_id":"c18yylknjsodb","chunk_label":"top_unit"},{"row":119,"row_count":1,"visible":true,"expansion_state":0,"options":{"engine":"r","label":"top_custoemrs","dev":"png"},"document_id":"2F1DCE16","chunk_id":"cb50g456p9vuz","chunk_label":"top_custoemrs"},{"row":147,"row_count":1,"visible":true,"expansion_state":0,"options":{"engine":"r","label":"unnamed-chunk-3","dev":"png"},"document_id":"2F1DCE16","chunk_id":"cphcmdv1dcp0c","chunk_label":"unnamed-chunk-1"},{"row":175,"row_count":1,"visible":true,"expansion_state":0,"options":{"engine":"r","label":"units-summary","dev":"png"},"document_id":"2F1DCE16","chunk_id":"cv3fuglwqz80w","chunk_label":"units-summary"}],"doc_write_time":0,"working_dir":null,"default_chunk_options":{"echo":false,"warning":false,"message":false}}